grabsys.py
pendulum.py
pendfetch-1.0.1.dist-info/METADATA
pendfetch-1.0.1.dist-info/WHEEL
pendfetch-1.0.1.dist-info/entry_points.txt
pendfetch-1.0.1.dist-info/top_level.txt
pendfetch-1.0.1.dist-info/RECORD
