Metadata-Version: 2.1
Name: pendfetch
Version: 1.0.1
Summary: A small double pendulum based neofetch clone
Home-page: https://github.com/Nekurone/double-pendulum-ascii/
Author: Nekurone
Author-email: florencesecure@protonmail.com
License: UNKNOWN
Platform: UNKNOWN
Classifier: Programming Language :: Python :: 3
Classifier: License :: OSI Approved :: GNU Lesser General Public License v2 (LGPLv2)
Classifier: Operating System :: OS Independent
Classifier: Intended Audience :: End Users/Desktop
Classifier: Topic :: Terminals
Requires-Python: >=3.6
Requires-Dist: windows-curses ; platform_system == "Windows"
